samara/__init__.py
samara/__main__.py
samara/alert/__init__.py
samara/alert/channels/__init__.py
samara/alert/channels/base.py
samara/alert/channels/email.py
samara/alert/channels/file.py
samara/alert/channels/http.py
samara/alert/controller.py
samara/alert/rules/__init__.py
samara/alert/rules/base.py
samara/alert/rules/env_vars_matches.py
samara/alert/rules/exception_regex.py
samara/alert/template.py
samara/alert/trigger.py
samara/cli.py
samara/exceptions.py
samara/settings.py
samara/telemetry.py
samara/types.py
samara/utils/__init__.py
samara/utils/file.py
samara/utils/http.py
samara/utils/logger.py
samara/workflow/__init__.py
samara/workflow/actions/__init__.py
samara/workflow/actions/base.py
samara/workflow/actions/http.py
samara/workflow/actions/move_or_copy_job_files.py
samara/workflow/controller.py
samara/workflow/jobs/__init__.py
samara/workflow/jobs/hooks.py
samara/workflow/jobs/models/__init__.py
samara/workflow/jobs/models/model_extract.py
samara/workflow/jobs/models/model_job.py
samara/workflow/jobs/models/model_load.py
samara/workflow/jobs/models/model_transform.py
samara/workflow/jobs/models/transforms/__init__.py
samara/workflow/jobs/models/transforms/model_aggregate.py
samara/workflow/jobs/models/transforms/model_cast.py
samara/workflow/jobs/models/transforms/model_distinct.py
samara/workflow/jobs/models/transforms/model_drop.py
samara/workflow/jobs/models/transforms/model_dropduplicates.py
samara/workflow/jobs/models/transforms/model_dropna.py
samara/workflow/jobs/models/transforms/model_filter.py
samara/workflow/jobs/models/transforms/model_groupby.py
samara/workflow/jobs/models/transforms/model_join.py
samara/workflow/jobs/models/transforms/model_orderby.py
samara/workflow/jobs/models/transforms/model_pivot.py
samara/workflow/jobs/models/transforms/model_select.py
samara/workflow/jobs/models/transforms/model_withcolumn.py
samara/workflow/jobs/polars/.gitkeep
samara/workflow/jobs/spark/__init__.py
samara/workflow/jobs/spark/extract.py
samara-0.2.dist-info/METADATA
samara-0.2.dist-info/WHEEL
samara-0.2.dist-info/licenses/LICENSE
samara-0.2.dist-info/RECORD
