Metadata-Version: 2.4
Name: Samara
Version: 0.2
Summary: Config Driven ETL Framework
License-File: LICENSE
Author: Krijn van der Burg
Requires-Python: >=3.13,<4.0
Classifier: Programming Language :: Python :: 3
Classifier: Programming Language :: Python :: 3.13
Classifier: Programming Language :: Python :: 3.14
Requires-Dist: click (>=8.1.0,<9.0.0)
Requires-Dist: email-validator (>=2.2.0,<3.0.0)
Requires-Dist: numpy (<2.0.0)
Requires-Dist: opentelemetry-api (>=1.37.0,<2.0.0)
Requires-Dist: opentelemetry-exporter-otlp (>=1.37.0,<2.0.0)
Requires-Dist: opentelemetry-sdk (>=1.37.0,<2.0.0)
Requires-Dist: pandas (>=2.3.0,<3.0.0)
Requires-Dist: pyarrow (==20.0.0)
Requires-Dist: pydantic (>=2.11.9,<3.0.0)
Requires-Dist: pydantic-settings (>=2.8.0,<3.0.0)
Requires-Dist: pyjson5 (>=1.6.9,<2.0.0)
Requires-Dist: pyspark (>=4.0.1,<5.0.0)
Requires-Dist: pyyaml (>=6.0.1,<7.0.0)
Requires-Dist: requests (>=2.32.5,<3.0.0)
Requires-Dist: structlog (>=25.4.0,<26.0.0)
